netrun/ratelimit/__init__.py
netrun/ratelimit/backends.py
netrun/ratelimit/bucket.py
netrun/ratelimit/config.py
netrun/ratelimit/decorators.py
netrun/ratelimit/exceptions.py
netrun/ratelimit/middleware.py
netrun/ratelimit/py.typed
netrun_ratelimit/__init__.py
netrun_ratelimit/backends.py
netrun_ratelimit/bucket.py
netrun_ratelimit/config.py
netrun_ratelimit/decorators.py
netrun_ratelimit/exceptions.py
netrun_ratelimit/middleware.py
netrun_ratelimit/py.typed
netrun_ratelimit-2.0.0.dist-info/METADATA
netrun_ratelimit-2.0.0.dist-info/WHEEL
netrun_ratelimit-2.0.0.dist-info/RECORD
