Metadata-Version: 2.4
Name: netrun-ratelimit
Version: 2.0.0
Summary: Distributed rate limiting with token bucket algorithm and Redis backend
Project-URL: Homepage, https://netrunsystems.com
Project-URL: Documentation, https://docs.netrunsystems.com/ratelimit
Project-URL: Repository, https://github.com/netrunsystems/netrun-ratelimit
Project-URL: Issues, https://github.com/netrunsystems/netrun-ratelimit/issues
Project-URL: Changelog, https://github.com/netrunsystems/netrun-ratelimit/blob/main/CHANGELOG.md
Author-email: Daniel Garza <daniel@netrunsystems.com>
Maintainer-email: Netrun Systems <engineering@netrunsystems.com>
License: MIT
Keywords: api,distributed,fastapi,middleware,rate-limiting,redis,throttling,token-bucket
Classifier: Development Status :: 5 - Production/Stable
Classifier: Framework :: FastAPI
Classifier: Intended Audience :: Developers
Classifier: License :: OSI Approved :: MIT License
Classifier: Operating System :: OS Independent
Classifier: Programming Language :: Python :: 3
Classifier: Programming Language :: Python :: 3.10
Classifier: Programming Language :: Python :: 3.11
Classifier: Programming Language :: Python :: 3.12
Classifier: Topic :: Internet :: WWW/HTTP :: HTTP Servers
Classifier: Topic :: Software Development :: Libraries :: Python Modules
Classifier: Typing :: Typed
Requires-Python: >=3.10
Requires-Dist: netrun-core>=2.0.0
Requires-Dist: pydantic-settings<3.0.0,>=2.0.0
Requires-Dist: pydantic<3.0.0,>=2.0.0
Provides-Extra: all
Requires-Dist: fastapi>=0.100.0; extra == 'all'
Requires-Dist: redis<6.0.0,>=5.0.0; extra == 'all'
Requires-Dist: starlette>=0.27.0; extra == 'all'
Provides-Extra: dev
Requires-Dist: black>=23.0.0; extra == 'dev'
Requires-Dist: fakeredis>=2.20.0; extra == 'dev'
Requires-Dist: httpx>=0.25.0; extra == 'dev'
Requires-Dist: mypy>=1.0.0; extra == 'dev'
Requires-Dist: pytest-asyncio>=0.21.0; extra == 'dev'
Requires-Dist: pytest-cov>=4.0.0; extra == 'dev'
Requires-Dist: pytest>=7.0.0; extra == 'dev'
Requires-Dist: ruff>=0.1.0; extra == 'dev'
Provides-Extra: fastapi
Requires-Dist: fastapi>=0.100.0; extra == 'fastapi'
Requires-Dist: starlette>=0.27.0; extra == 'fastapi'
Provides-Extra: redis
Requires-Dist: redis<6.0.0,>=5.0.0; extra == 'redis'
